LICENSE
MANIFEST.in
README.md
README.rst
requirements.txt
setup.py
pdml2flow_frame_inter_arrival_time.egg-info/PKG-INFO
pdml2flow_frame_inter_arrival_time.egg-info/SOURCES.txt
pdml2flow_frame_inter_arrival_time.egg-info/dependency_links.txt
pdml2flow_frame_inter_arrival_time.egg-info/entry_points.txt
pdml2flow_frame_inter_arrival_time.egg-info/requires.txt
pdml2flow_frame_inter_arrival_time.egg-info/top_level.txt
plugin/__init__.py
plugin/plugin.py