Metadata-Version: 1.0
Name: pdml2flow-frame-inter-arrival-time
Version: 0.1
Summary: Calculate frame inter arrival times
Home-page: https://github.com/Enteee/pdml2flow-frame-inter-arrival-time
Author: Ente
Author-email: ducksource@duckpond.ch
License: Apache 2.0
Keywords: pdml2flow plugin
Platform: UNKNOWN
